moocxing_lite/MXMedia.py
moocxing_lite/MXMqtt.py
moocxing_lite/MXNLP.py
moocxing_lite/MXSerial.py
moocxing_lite/MXSpeech.py
moocxing_lite/MXThread.py
moocxing_lite/__init__.py
moocxing_lite/moocxing.py
moocxing_lite-0.0.8.dist-info/METADATA
moocxing_lite-0.0.8.dist-info/WHEEL
moocxing_lite-0.0.8.dist-info/top_level.txt
moocxing_lite-0.0.8.dist-info/RECORD
